{
  "id": "whitesnake-is-this-love",
  "title": "Is This Love",
  "artist": "Whitesnake",
  "originalKey": "Em",
  "tempo": "Slow",
  "timeSignature": "4/4",
  "content": [
    {
      "type": "section",
      "name": "INTRO",
      "lines": [
        {
          "type": "chords",
          "content": ["Em7", "-"]
        },
        {
          "type": "text",
          "content": "(Riff de guitarra limpia)"
        }
      ]
    },
    {
      "type": "divider"
    },
    {
      "type": "section",
      "name": "VERSO 1",
      "lines": [
        {
          "type": "voice",
          "name": "1º VOZ 1",
          "color": "ale",
          "lines": [
            {
              "type": "chord",
              "content": "Em7"
            },
            {
              "type": "lyric",
              "content": "Should've known better"
            },
            {
              "type": "chord",
              "content": "Bm7"
            },
            {
              "type": "lyric",
              "content": "Than to let you go alone"
            },
            {
              "type": "chord",
              "content": "C9"
            },
            {
              "type": "lyric",
              "content": ""
            }
          ]
        },
        {
          "type": "voice",
          "name": "1º VOZ 2",
          "color": "pato",
          "lines": [
            {
              "type": "chord",
              "content": "Em7"
            },
            {
              "type": "lyric",
              "content": "In times like these"
            },
            {
              "type": "chord",
              "content": "Bm7"
            },
            {
              "type": "lyric",
              "content": "I can't make it on my own"
            },
            {
              "type": "chord",
              "content": "C9"
            },
            {
              "type": "lyric",
              "content": ""
            }
          ]
        },
        {
          "type": "chords",
          "content": ["Em7", "Bm7", "C9"]
        },
        {
          "type": "lyric",
          "content": "Wasted days and sleepless nights"
        },
        {
          "type": "chords",
          "content": ["C7M", "Bm7", "Am7", "G7M", "F9"]
        },
        {
          "type": "lyric",
          "content": "And I can't wait to see you again"
        }
      ]
    },
    {
      "type": "divider"
    },
    {
      "type": "section",
      "name": "VERSO 2",
      "lines": [
        {
          "type": "voice",
          "name": "1º VOZ 1",
          "color": "ale",
          "lines": [
            {
              "type": "chord",
              "content": "Em7"
            },
            {
              "type": "lyric",
              "content": "I find I spend my time"
            },
            {
              "type": "chord",
              "content": "Bm7"
            },
            {
              "type": "lyric",
              "content": "Waiting on your call"
            },
            {
              "type": "chord",
              "content": "C9"
            },
            {
              "type": "lyric",
              "content": ""
            }
          ]
        },
        {
          "type": "voice",
          "name": "1º VOZ 2",
          "color": "pato",
          "lines": [
            {
              "type": "chord",
              "content": "Em7"
            },
            {
              "type": "lyric",
              "content": "How can I tell you baby"
            },
            {
              "type": "chord",
              "content": "Bm7"
            },
            {
              "type": "lyric",
              "content": "My back's against the wall"
            },
            {
              "type": "chord",
              "content": "C9"
            },
            {
              "type": "lyric",
              "content": ""
            }
          ]
        },
        {
          "type": "chords",
          "content": ["Em7", "Bm7", "C9"]
        },
        {
          "type": "lyric",
          "content": "I need you by my side"
        },
        {
          "type": "chords",
          "content": ["Bm7", "C9"]
        },
        {
          "type": "lyric",
          "content": "To tell me it's alright"
        },
        {
          "type": "chords",
          "content": ["C7M", "Bm7", "Am7", "G7M", "F9", "F9"]
        },
        {
          "type": "lyric",
          "content": "Cause I don't think I can take anymore"
        }
      ]
    },
    {
      "type": "divider"
    },
    {
      "type": "section",
      "name": "ESTRIBILLO",
      "lines": [
        {
          "type": "voice",
          "name": "1º VOZ 1",
          "color": "ale",
          "lines": [
            {
              "type": "chord",
              "content": "C9"
            },
            {
              "type": "lyric",
              "content": "Is this love that I'm feeling?"
            }
          ]
        },
        {
          "type": "voice",
          "name": "2º VOZ 2",
          "color": "pato",
          "lines": [
            {
              "type": "chord",
              "content": "D/C"
            },
            {
              "type": "lyric",
              "content": ""
            }
          ]
        },
        {
          "type": "chords",
          "content": ["Bm7", "C", "Bm7", "Am7", "G7M"]
        },
        {
          "type": "lyric",
          "content": "Is this the love that I've been searching for?"
        },
        {
          "type": "chords",
          "content": ["C9", "D/C"]
        },
        {
          "type": "lyric",
          "content": "Is it love or am I dreaming?"
        },
        {
          "type": "chords",
          "content": ["Bm7"]
        },
        {
          "type": "lyric",
          "content": "This must be love"
        },
        {
          "type": "chords",
          "content": ["C7M", "Bm7", "Am7", "G7M", "F7M"]
        },
        {
          "type": "lyric",
          "content": "Cause it's really got a hold on me"
        },
        {
          "type": "chords",
          "content": ["F7M"]
        },
        {
          "type": "lyric",
          "content": "A hold on me"
        }
      ]
    },
    {
      "type": "divider"
    },
    {
      "type": "section",
      "name": "VERSO 3",
      "lines": [
        {
          "type": "voice",
          "name": "1º VOZ 1",
          "color": "ale",
          "lines": [
            {
              "type": "chord",
              "content": "Em7"
            },
            {
              "type": "lyric",
              "content": "I can't stop the feeling"
            },
            {
              "type": "chord",
              "content": "Bm7"
            },
            {
              "type": "lyric",
              "content": "I've been this way before"
            },
            {
              "type": "chord",
              "content": "C9"
            },
            {
              "type": "lyric",
              "content": ""
            }
          ]
        },
        {
          "type": "voice",
          "name": "1º VOZ 2",
          "color": "pato",
          "lines": [
            {
              "type": "chord",
              "content": "Em7"
            },
            {
              "type": "lyric",
              "content": "But with you I found the key"
            },
            {
              "type": "chord",
              "content": "Bm7"
            },
            {
              "type": "lyric",
              "content": "To open any door"
            },
            {
              "type": "chord",
              "content": "C9"
            },
            {
              "type": "lyric",
              "content": ""
            }
          ]
        },
        {
          "type": "chords",
          "content": ["Em7", "Bm7", "C9"]
        },
        {
          "type": "lyric",
          "content": "I can feel my love for you"
        },
        {
          "type": "chords",
          "content": ["Bm7", "C9"]
        },
        {
          "type": "lyric",
          "content": "Growing stronger day by day"
        },
        {
          "type": "chords",
          "content": ["C7M", "Bm7", "Am7", "G7M", "F9"]
        },
        {
          "type": "lyric",
          "content": "And I can't wait to see you again"
        },
        {
          "type": "chords",
          "content": ["F9"]
        },
        {
          "type": "lyric",
          "content": "So I can hold you in my arms"
        }
      ]
    },
    {
      "type": "divider"
    },
    {
      "type": "section",
      "name": "ESTRIBILLO FINAL (x3)",
      "lines": [
        {
          "type": "voice",
          "name": "1º VOZ 1",
          "color": "ale",
          "lines": [
            {
              "type": "chord",
              "content": "C9"
            },
            {
              "type": "lyric",
              "content": "Is this love that I'm feeling?"
            }
          ]
        },
        {
          "type": "voice",
          "name": "2º VOZ 2",
          "color": "pato",
          "lines": [
            {
              "type": "chord",
              "content": "D/C"
            },
            {
              "type": "lyric",
              "content": ""
            }
          ]
        },
        {
          "type": "chords",
          "content": ["Bm7", "C", "Bm7", "Am7", "G"]
        },
        {
          "type": "lyric",
          "content": "Is this the love that I've been searching for?"
        },
        {
          "type": "chords",
          "content": ["C9", "D/C"]
        },
        {
          "type": "lyric",
          "content": "Is it love or am I dreaming?"
        },
        {
          "type": "chords",
          "content": ["Bm7", "C", "Bm7", "Am7", "G"]
        },
        {
          "type": "lyric",
          "content": "Is this the love that I've been searching for?"
        }
      ]
    },
    {
      "type": "divider"
    },
    {
      "type": "section",
      "name": "OUTRO",
      "lines": [
        {
          "type": "chords",
          "content": ["Em7", "-"]
        },
        {
          "type": "text",
          "content": "(Riff final - Desvanecimiento)"
        }
      ]
    }
  ]
}
