{
    "id": "charly-garcia-himno-nacional-argentino-a",
    "title": "Himno Nacional Argentino",
    "artist": "Charly García",
    "originalKey": "A",
    "tempo": "Moderate",
    "timeSignature": "4/4",
    "content": [
      {
        "type": "section",
        "name": "INTRO",
        "lines": [
          {
            "type": "chords",
            "content": ["A", "E", "A"]
          }
        ]
      },
      {
        "type": "divider"
      },
      {
        "type": "voice",
        "name": "1º VOZ 1",
        "color": "ale",
        "lines": [
          {
            "type": "chord",
            "content": "A"
          },
          {
            "type": "lyric",
            "content": "Oíd, mortales, el grito sagrado:"
          }
        ]
      },
      {
        "type": "voice",
        "name": "1º VOZ 2",
        "color": "pato",
        "lines": [
          {
            "type": "chord",
            "content": "A7"
          },
          {
            "type": "lyric",
            "content": "¡Libertad, libertad, libertad!"
          },
          {
            "type": "chords",
            "content": ["D", "E", "E7", "A"]
          }
        ]
      },
      {
        "type": "divider"
      },
      {
        "type": "voice",
        "name": "1º VOZ 1",
        "color": "ale",
        "lines": [
          {
            "type": "chord",
            "content": "A"
          },
          {
            "type": "lyric",
            "content": "Oíd el ruido de rotas cadenas,"
          },
          {
            "type": "chord",
            "content": "B7"
          },
          {
            "type": "lyric",
            "content": "ved en trono a la noble igualdad."
          },
          {
            "type": "chords",
            "content": ["E", "E7"]
          }
        ]
      },
      {
        "type": "divider"
      },
      {
        "type": "voice",
        "name": "1º VOZ 1",
        "color": "ale",
        "lines": [
          {
            "type": "chord",
            "content": "D"
          },
          {
            "type": "lyric",
            "content": "Ya su trono dignísimo abrieron"
          },
          {
            "type": "chords",
            "content": ["Am", "Dm", "F", "E"]
          }
        ]
      },
      {
        "type": "voice",
        "name": "1º VOZ 2",
        "color": "pato",
        "lines": [
          {
            "type": "chord",
            "content": "E7"
          },
          {
            "type": "lyric",
            "content": "las provincias unidas del Sud,"
          },
          {
            "type": "chords",
            "content": ["Am", "Am/G", "F", "B7", "E", "E7"]
          }
        ]
      },
      {
        "type": "divider"
      },
      {
        "type": "voice",
        "name": "1º VOZ 1",
        "color": "ale",
        "lines": [
          {
            "type": "chord",
            "content": "Am"
          },
          {
            "type": "lyric",
            "content": "Y los libres del mundo responden:"
          },
          {
            "type": "chords",
            "content": ["E", "Am"]
          }
        ]
      },
      {
        "type": "voice",
        "name": "1º VOZ 2",
        "color": "pato",
        "lines": [
          {
            "type": "chord",
            "content": "Am"
          },
          {
            "type": "lyric",
            "content": "al gran pueblo argentino salud,"
          },
          {
            "type": "chords",
            "content": ["Am/G", "F", "B7", "E", "E7"]
          }
        ]
      },
      {
        "type": "divider"
      },
      {
        "type": "voice",
        "name": "1º VOZ 1",
        "color": "ale",
        "lines": [
          {
            "type": "chord",
            "content": "A"
          },
          {
            "type": "lyric",
            "content": "Y los libres del mundo responden:"
          },
          {
            "type": "chords",
            "content": ["F#m", "Bm", "A"]
          }
        ]
      },
      {
        "type": "voice",
        "name": "1º VOZ 2",
        "color": "pato",
        "lines": [
          {
            "type": "chord",
            "content": "Dm"
          },
          {
            "type": "lyric",
            "content": "al gran pueblo argentino salud."
          },
          {
            "type": "chords",
            "content": ["A", "E", "A"]
          }
        ]
      },
      {
        "type": "divider"
      },
      {
        "type": "section",
        "name": "INSTRUMENTAL",
        "lines": [
          {
            "type": "chords",
            "content": ["E", "E", "A", "A", "E", "E", "A", "A", "A"]
          }
        ]
      },
      {
        "type": "divider"
      },
      {
        "type": "section",
        "name": "SEGUNDA PARTE",
        "lines": [
          {
            "type": "chords",
            "content": ["A", "E", "A", "D", "E", "A", "A"]
          }
        ]
      },
      {
        "type": "divider"
      },
      {
        "type": "voice",
        "name": "1º VOZ 1",
        "color": "ale",
        "lines": [
          {
            "type": "chord",
            "content": "A"
          },
          {
            "type": "lyric",
            "content": "Sean eternos los laureles"
          }
        ]
      },
      {
        "type": "voice",
        "name": "1º VOZ 2",
        "color": "pato",
        "lines": [
          {
            "type": "chord",
            "content": "A"
          },
          {
            "type": "lyric",
            "content": "que supimos conseguir,"
          }
        ]
      },
      {
        "type": "divider"
      },
      {
        "type": "voice",
        "name": "1º VOZ 1",
        "color": "ale",
        "lines": [
          {
            "type": "chord",
            "content": "D"
          },
          {
            "type": "lyric",
            "content": "que supimos conseguir..."
          },
          {
            "type": "chords",
            "content": ["B7", "E", "E7"]
          }
        ]
      },
      {
        "type": "divider"
      },
      {
        "type": "voice",
        "name": "1º VOZ 1",
        "color": "ale",
        "lines": [
          {
            "type": "chord",
            "content": "F#m"
          },
          {
            "type": "lyric",
            "content": "Coronados de gloria vivamos,"
          },
          {
            "type": "chords",
            "content": ["Bm", "A", "B7", "E"]
          }
        ]
      },
      {
        "type": "voice",
        "name": "1º VOZ 2",
        "color": "pato",
        "lines": [
          {
            "type": "chord",
            "content": "A"
          },
          {
            "type": "lyric",
            "content": "o juremos con gloria morir."
          },
          {
            "type": "chords",
            "content": ["E", "A"]
          }
        ]
      },
      {
        "type": "divider"
      },
      {
        "type": "section",
        "name": "FINAL",
        "lines": [
          {
            "type": "chords",
            "content": ["D", "A", "E", "A"]
          },
          {
            "type": "lyric",
            "content": "O juremos con gloria morir."
          },
          {
            "type": "chords",
            "content": ["D", "A", "E", "A"]
          },
          {
            "type": "lyric",
            "content": "O juremos con gloria morir."
          }
        ]
      }
    ]
  }
  